pycounts_mpbm/__init__.py
pycounts_mpbm/plotting.py
pycounts_mpbm/pycounts_mpbm.py
pycounts_mpbm-0.1.2.dist-info/LICENSE
pycounts_mpbm-0.1.2.dist-info/METADATA
pycounts_mpbm-0.1.2.dist-info/WHEEL
pycounts_mpbm-0.1.2.dist-info/RECORD
